OnedriveCMD-0.1.0.dist-info/DESCRIPTION.rst
OnedriveCMD-0.1.0.dist-info/METADATA
OnedriveCMD-0.1.0.dist-info/RECORD
OnedriveCMD-0.1.0.dist-info/WHEEL
OnedriveCMD-0.1.0.dist-info/entry_points.txt
OnedriveCMD-0.1.0.dist-info/metadata.json
OnedriveCMD-0.1.0.dist-info/top_level.txt
onedrivecmd/__init__.py
onedrivecmd/onedrivecmd.py
onedrivecmd/utils/__init__.py
onedrivecmd/utils/actions.py
onedrivecmd/utils/arguments.py
onedrivecmd/utils/helper_file.py
onedrivecmd/utils/helper_item.py
onedrivecmd/utils/session.py
onedrivecmd/utils/static.py
onedrivecmd/utils/uploader.py
